{
	"Team": 
	{
		"Name": "London Monarchs",
		"Squad" :
		[
{"Player": {"Name":"Young", "Position":"Quarterback", "Age":2, "Level":12, "Q":40, "S:":30, "T:":30, "Experience:":	-1.05}},
{"Player": {"Name":"Montana", "Position":"Quarterback", "Age":2, "Level":12, "Q":20, "S:":20, "T:":60, "Experience:":	-0.15}},
{"Player": {"Name":"Jones", "Position":"Running Back", "Age":9, "Level":5, "Q":60, "S:":20, "T:":20, "Experience:":	-1.35}},
{"Player": {"Name":"Simpson", "Position":"Running Back", "Age":2, "Level":13, "Q":30, "S:":40, "T:":30, "Experience:":	0}},
{"Player": {"Name":"Perry", "Position":"Running Back", "Age":3, "Level":6, "Q":40, "S:":40, "T:":20, "Experience:":	-1.45}},
{"Player": {"Name":"Rice", "Position":"Wide Receiver", "Age":4, "Level":11, "Q":50, "S:":0, "T:":50, "Experience:":	-0.05}},
{"Player": {"Name":"Mulkey", "Position":"Wide Receiver", "Age":6, "Level":5, "Q":70, "S:":0, "T:":30, "Experience:":	-0.9}},
{"Player": {"Name":"Robey", "Position":"Wide Receiver", "Age":5, "Level":5, "Q":70, "S:":0, "T:":30, "Experience:":	-1.5}},
{"Player": {"Name":"Monk", "Position":"Wide Receiver", "Age":2, "Level":12, "Q":70, "S:":0, "T:":30, "Experience:":	-0.5}},
{"Player": {"Name":"Swann", "Position":"Wide Receiver", "Age":6, "Level":4, "Q":60, "S:":0, "T:":40, "Experience:":	-1.5}},
{"Player": {"Name":"Irvin", "Position":"Wide Receiver", "Age":4, "Level":7, "Q":70, "S:":0, "T:":30, "Experience:":	-1.35}},
{"Player": {"Name":"Ganzi", "Position":"Tight End", "Age":1, "Level":8, "Q":35, "S:":35, "T:":30, "Experience:":	-0.55}},
{"Player": {"Name":"Sharpe", "Position":"Tight End", "Age":3, "Level":11, "Q":50, "S:":30, "T:":20, "Experience:":	0.05}},
{"Player": {"Name":"Ringo", "Position":"Center", "Age":2, "Level":11, "Q":40, "S:":55, "T:":5, "Experience:":	-0.3}},
{"Player": {"Name":"Kiesling", "Position":"Offensive Guard", "Age":4, "Level":7, "Q":40, "S:":60, "T:":0, "Experience:":	-1.05}},
{"Player": {"Name":"Fortmann", "Position":"Offensive Guard", "Age":3, "Level":6, "Q":50, "S:":50, "T:":0, "Experience:":	-0.75}},
{"Player": {"Name":"Merlos", "Position":"Offensive Guard", "Age":1, "Level":8, "Q":45, "S:":55, "T:":0, "Experience:":	-0.9}},
{"Player": {"Name":"Mack", "Position":"Offensive Guard", "Age":6, "Level":9, "Q":50, "S:":50, "T:":0, "Experience:":	-0.1}},
{"Player": {"Name":"Percy", "Position":"Offensive Tackle", "Age":0, "Level":8, "Q":60, "S:":40, "T:":0, "Experience:":	-1.4}},
{"Player": {"Name":"Cheng", "Position":"Offensive Tackle", "Age":4, "Level":5, "Q":50, "S:":50, "T:":0, "Experience:":	-0.95}},
{"Player": {"Name":"Yary", "Position":"Offensive Tackle", "Age":4, "Level":5, "Q":60, "S:":40, "T:":0, "Experience:":	-1.45}},
{"Player": {"Name":"Mackenzie", "Position":"Offensive Tackle", "Age":1, "Level":13, "Q":60, "S:":40, "T:":0, "Experience:":	-0.3}},
{"Player": {"Name":"Shell", "Position":"Offensive Tackle", "Age":8, "Level":8, "Q":60, "S:":40, "T:":0, "Experience:":	-0.5}},
{"Player": {"Name":"St Clair", "Position":"Offensive Tackle", "Age":6, "Level":9, "Q":50, "S:":50, "T:":0, "Experience:":	-0.5}},
{"Player": {"Name":"Youngblood", "Position":"Defensive End", "Age":4, "Level":7, "Q":40, "S:":60, "T:":0, "Experience:":	-1.2}},
{"Player": {"Name":"Nero", "Position":"Defensive End", "Age":1, "Level":6, "Q":60, "S:":40, "T:":0, "Experience:":	-0.84}},
{"Player": {"Name":"Langston", "Position":"Defensive End", "Age":3, "Level":4, "Q":40, "S:":60, "T:":0, "Experience:":	-1.4}},
{"Player": {"Name":"Dent", "Position":"Defensive End", "Age":6, "Level":3, "Q":60, "S:":40, "T:":0, "Experience:":	-1.12}},
{"Player": {"Name":"Cambiaso", "Position":"Defensive End", "Age":1, "Level":11, "Q":55, "S:":45, "T:":0, "Experience:":	-0.35}},
{"Player": {"Name":"Ulloa", "Position":"Defensive Tackle", "Age":1, "Level":8, "Q":45, "S:":55, "T:":0, "Experience:":	-0.65}},
{"Player": {"Name":"Nomellini", "Position":"Defensive Tackle", "Age":4, "Level":11, "Q":40, "S:":60, "T:":0, "Experience:":	0.05}},
{"Player": {"Name":"Jones", "Position":"Inside Linebacker", "Age":0, "Level":8, "Q":0, "S:":25, "T:":75, "Experience:":	-1.02}},
{"Player": {"Name":"Butkus", "Position":"Inside Linebacker", "Age":5, "Level":5, "Q":0, "S:":40, "T:":60, "Experience:":	-1.36}},
{"Player": {"Name":"Wilcox", "Position":"Inside Linebacker", "Age":3, "Level":10, "Q":0, "S:":40, "T:":60, "Experience:":	-0.05}},
{"Player": {"Name":"Ryan", "Position":"Inside Linebacker", "Age":0, "Level":6, "Q":0, "S:":30, "T:":70, "Experience:":	-1.12}},
{"Player": {"Name":"Simons", "Position":"Inside Linebacker", "Age":0, "Level":4, "Q":0, "S:":30, "T:":70, "Experience:":	-1.12}},
{"Player": {"Name":"Hewitson", "Position":"Outside Linebacker", "Age":7, "Level":4, "Q":30, "S:":70, "T:":0, "Experience:":	-0.8}},
{"Player": {"Name":"George", "Position":"Outside Linebacker", "Age":2, "Level":11, "Q":40, "S:":60, "T:":0, "Experience:":	-0.55}},
{"Player": {"Name":"Heilman", "Position":"Outside Linebacker", "Age":8, "Level":5, "Q":30, "S:":70, "T:":0, "Experience:":	-0.9}},
{"Player": {"Name":"Tims", "Position":"Outside Linebacker", "Age":0, "Level":6, "Q":20, "S:":80, "T:":0, "Experience:":	-1.06}},
{"Player": {"Name":"Welsh", "Position":"Outside Linebacker", "Age":0, "Level":5, "Q":45, "S:":55, "T:":0, "Experience:":	-1.02}},
{"Player": {"Name":"Renfo", "Position":"Safety", "Age":5, "Level":2, "Q":20, "S:":20, "T:":60, "Experience:":	-0.84}},
{"Player": {"Name":"Wilson", "Position":"Safety", "Age":3, "Level":10, "Q":50, "S:":30, "T:":20, "Experience:":	-0.65}},
{"Player": {"Name":"Monteverde", "Position":"Safety", "Age":1, "Level":11, "Q":45, "S:":20, "T:":35, "Experience:":	-0.7}},
{"Player": {"Name":"Hitman", "Position":"Safety", "Age":0, "Level":9, "Q":25, "S:":20, "T:":55, "Experience:":	-1.16}},
{"Player": {"Name":"Woodson", "Position":"Safety", "Age":10, "Level":8, "Q":20, "S:":20, "T:":60, "Experience:":	-0.94}},
{"Player": {"Name":"Joose", "Position":"Safety", "Age":0, "Level":6, "Q":20, "S:":60, "T:":20, "Experience:":	-1.16}},
{"Player": {"Name":"Lott", "Position":"Safety", "Age":6, "Level":9, "Q":50, "S:":30, "T:":20, "Experience:":	-0.55}},
{"Player": {"Name":"Jonson", "Position":"Cornerback", "Age":5, "Level":6, "Q":80, "S:":0, "T:":20, "Experience:":	-0.55}},
{"Player": {"Name":"Thomas", "Position":"Cornerback", "Age":3, "Level":8, "Q":70, "S:":0, "T:":30, "Experience:":	-0.15}},
{"Player": {"Name":"Mannix", "Position":"Cornerback", "Age":1, "Level":9, "Q":75, "S:":0, "T:":25, "Experience:":	-0.88}},
{"Player": {"Name":"Stenerud", "Position":"Kicker", "Age":5, "Level":5, "Q":0, "S:":50, "T:":50, "Experience:": 0}},
{"Player": {"Name":"Berry", "Position":"Kicker", "Age":10, "Level":9, "Q":0, "S:":50, "T:":50, "Experience:": 0}},
{"Player": {"Name":"Marquis", "Position":"Punter", "Age":10, "Level":5, "Q":0, "S:":50, "T:":50, "Experience:": 0}},
{"Player": {"Name":"Shurville", "Position":"Punter", "Age":1, "Level":4, "Q":0, "S:":55, "T:":45, "Experience:": 0}},
{"Player": {"Name":"Sanders", "Position":"Returner", "Age":2, "Level":12, "Q":20, "S:":0, "T:":80, "Experience:":	-0.95}},
{"Player": {"Name":"Murrey", "Position":"Returner", "Age":1, "Level":9, "Q":45, "S:":0, "T:":55, "Experience:":	-1.5}}
		]
	}
}

